atomicmixer/__init__.py
atomicmixer/__main__.py
atomicmixer/images/arrow.png
atomicmixer/images/bitcoin.png
atomicmixer/images/bitcoin_black.png
atomicmixer-0.1.3.dist-info/LICENSE
atomicmixer-0.1.3.dist-info/METADATA
atomicmixer-0.1.3.dist-info/WHEEL
atomicmixer-0.1.3.dist-info/entry_points.txt
atomicmixer-0.1.3.dist-info/top_level.txt
atomicmixer-0.1.3.dist-info/RECORD
