Metadata-Version: 2.1
Name: atomicmixer
Version: 0.1.3
Summary: AtomicMixerRefundTool
Home-page: https://github.com/TannhauserGate420/atomicMixerRefundTool
Author: iizegrim
Author-email: iizegrim@protonmail.com
Keywords: atomicmixer,atomicblender,atomicswap,atomic,swap,bitcoin,lightning,cryptocurrencies,cryptocurrency,refund,refundtool
Classifier: Development Status :: 3 - Alpha
Classifier: Environment :: X11 Applications :: Qt
Classifier: Intended Audience :: End Users/Desktop
Classifier: License :: OSI Approved :: GNU General Public License v3 (GPLv3)
Classifier: Operating System :: MacOS
Classifier: Operating System :: Microsoft :: Windows
Classifier: Operating System :: POSIX
Classifier: Programming Language :: Python :: 3 :: Only
Classifier: Topic :: Utilities
Requires-Python: >=3.8, <4
License-File: LICENSE
Requires-Dist: python-bitcoinlib
Requires-Dist: requests
Requires-Dist: emoji
Requires-Dist: PyQt5
Requires-Dist: fake-http-header
